teamchain/__init__.py
teamchain/vector_database/__init__.py
teamchain/vector_database/in_memory.py
easyagent-0.0.0.dist-info/METADATA
easyagent-0.0.0.dist-info/WHEEL
easyagent-0.0.0.dist-info/top_level.txt
easyagent-0.0.0.dist-info/RECORD
