Metadata-Version: 2.1
Name: easyagent
Version: 0.0.0
Summary: Description of my package
Home-page: https://github.com/mypackage.git
Author: Jacky Wong
Author-email: colabdog@gmail.com
